huaweicloudsdkies/__init__.py
huaweicloudsdkies/v1/__init__.py
huaweicloudsdkies/v1/ies_async_client.py
huaweicloudsdkies/v1/ies_client.py
huaweicloudsdkies/v1/model/__init__.py
huaweicloudsdkies/v1/model/charge_mode.py
huaweicloudsdkies/v1/model/compute_spec.py
huaweicloudsdkies/v1/model/condition.py
huaweicloudsdkies/v1/model/create_edge_site.py
huaweicloudsdkies/v1/model/create_edge_site_request.py
huaweicloudsdkies/v1/model/create_edge_site_request_body.py
huaweicloudsdkies/v1/model/create_edge_site_response.py
huaweicloudsdkies/v1/model/create_location.py
huaweicloudsdkies/v1/model/delete_edge_site_request.py
huaweicloudsdkies/v1/model/delete_edge_site_response.py
huaweicloudsdkies/v1/model/edge_site_detail.py
huaweicloudsdkies/v1/model/list_edge_site_metrics_request.py
huaweicloudsdkies/v1/model/list_edge_site_metrics_response.py
huaweicloudsdkies/v1/model/list_edge_sites_request.py
huaweicloudsdkies/v1/model/list_edge_sites_response.py
huaweicloudsdkies/v1/model/list_quotas_request.py
huaweicloudsdkies/v1/model/list_quotas_response.py
huaweicloudsdkies/v1/model/list_racks_request.py
huaweicloudsdkies/v1/model/list_racks_response.py
huaweicloudsdkies/v1/model/list_storage_pools_request.py
huaweicloudsdkies/v1/model/list_storage_pools_response.py
huaweicloudsdkies/v1/model/list_supported_regions_request.py
huaweicloudsdkies/v1/model/list_supported_regions_response.py
huaweicloudsdkies/v1/model/location_detail.py
huaweicloudsdkies/v1/model/market_options.py
huaweicloudsdkies/v1/model/metric_data_detail.py
huaweicloudsdkies/v1/model/metric_data_detail_dimension.py
huaweicloudsdkies/v1/model/page_info.py
huaweicloudsdkies/v1/model/pay_mode.py
huaweicloudsdkies/v1/model/prepaid_options.py
huaweicloudsdkies/v1/model/quota_detail.py
huaweicloudsdkies/v1/model/quota_resources.py
huaweicloudsdkies/v1/model/rack.py
huaweicloudsdkies/v1/model/rack_info.py
huaweicloudsdkies/v1/model/rack_status.py
huaweicloudsdkies/v1/model/region_detail.py
huaweicloudsdkies-3.1.58.dist-info/LICENSE
huaweicloudsdkies-3.1.58.dist-info/METADATA
huaweicloudsdkies-3.1.58.dist-info/WHEEL
huaweicloudsdkies-3.1.58.dist-info/top_level.txt
huaweicloudsdkies-3.1.58.dist-info/RECORD
